MANIFEST.in
README.rst
ez_setup.py
setup.py
sempy/__init__.py
sempy.egg-info/PKG-INFO
sempy.egg-info/SOURCES.txt
sempy.egg-info/dependency_links.txt
sempy.egg-info/top_level.txt
sempy/basic/__init__.py
sempy/basic/basic.py
sempy/basic/basic_f90.so
sempy/fluid/__init__.py
sempy/fluid/fluid.py
sempy/fluid/fluid_def_f90.so
sempy/fluid/fluid_f90.so
sempy/fluid/fluid_operator_f90.so
sempy/linsolvers/__init__.py
sempy/linsolvers/solvers.py
sempy/ode/__init__.py
sempy/ode/multistep.py
sempy/ode/ode_f90.so
sempy/ode/oifs.py
sempy/ode/prk.py
sempy/ode/strang.py
sempy/operators/__init__.py
sempy/operators/operators_f90.so
sempy/operators/operators_main.py
sempy/operators/one_d/__init__.py
sempy/operators/one_d/operators1d.py
sempy/precond/__init__.py
sempy/precond/precond_f90.so
sempy/precond/precond_main.py
sempy/solvers/__init__.py
sempy/solvers/navier_stokes.py
sempy/solvers/navier_stokes_oifs.py
sempy/solvers/projection.py
sempy/solvers/stokes_solver.py
sempy/space/__init__.py
sempy/space/function_vec.py
sempy/space/plot.py
sempy/space/space.py
sempy/space/space_f90.so
sempy/space/mesh_lib/__init__.py
sempy/space/mesh_lib/gmsh/__init__.py
sempy/space/mesh_lib/gmsh/cube.geo
sempy/space/mesh_lib/gmsh/cube.msh
sempy/space/mesh_lib/gmsh/line.geo
sempy/space/mesh_lib/gmsh/line.msh
sempy/space/mesh_lib/gmsh/square.geo
sempy/space/mesh_lib/gmsh/square.msh
sempy/space/mesh_lib/gmsh/square_neumann.geo
sempy/space/mesh_lib/gmsh/square_neumann.msh
sempy/space/one_d/__init__.py
sempy/space/one_d/gmsh1D.py
sempy/space/three_d/__init__.py
sempy/space/three_d/gmsh3D.py
sempy/space/two_d/__init__.py
sempy/space/two_d/gmsh2D.py
sempy/tests/__init__.py
sempy/tests/convdiff.py
sempy/tests/navier_stokes.py
sempy/tests/test.py